bpgfx.py
braille_pattern_graphics-1.0.0.dist-info/LICENSE
braille_pattern_graphics-1.0.0.dist-info/METADATA
braille_pattern_graphics-1.0.0.dist-info/WHEEL
braille_pattern_graphics-1.0.0.dist-info/top_level.txt
braille_pattern_graphics-1.0.0.dist-info/RECORD
