Metadata-Version: 2.1
Name: braille-pattern-graphics
Version: 1.0.0
Summary: 2D graphics using braille patterns
Home-page: https://github.com/ash-nolan/braille-pattern-graphics
Author: ashn
Author-email: <me@ashn.dev>
License: UNKNOWN
Platform: UNKNOWN
